{
  "id": "ipl26_m37",
  "wk": 5,
  "title": "37th Match",
  "teams": [
    "CSK",
    "GT"
  ],
  "date": "Apr 26",
  "status": "completed",
  "scores": {
    "c09": {
      "played": true,
      "runs": 11,
      "balls": 15,
      "fours": 2,
      "sixes": 0,
      "got_out": 1,
      "duck": 0,
      "overs": 0.0,
      "runs_conceded": 0,
      "wickets": 0,
      "maidens": 0,
      "lbw_bowled": 0,
      "catches": 0,
      "stumpings": 1,
      "run_out_direct": 0,
      "run_out_assist": 0
    },
    "c01": {
      "played": true,
      "runs": 74,
      "balls": 60,
      "fours": 6,
      "sixes": 4,
      "got_out": 0,
      "duck": 0,
      "overs": 0.0,
      "runs_conceded": 0,
      "wickets": 0,
      "maidens": 0,
      "lbw_bowled": 0,
      "catches": 0,
      "stumpings": 0,
      "run_out_direct": 0,
      "run_out_assist": 0
    },
    "c16": {
      "played": true,
      "runs": 4,
      "balls": 3,
      "fours": 1,
      "sixes": 0,
      "got_out": 1,
      "duck": 0,
      "overs": 0.0,
      "runs_conceded": 0,
      "wickets": 0,
      "maidens": 0,
      "lbw_bowled": 0,
      "catches": 0,
      "stumpings": 0,
      "run_out_direct": 0,
      "run_out_assist": 0
    },
    "c15": {
      "played": true,
      "runs": 0,
      "balls": 1,
      "fours": 0,
      "sixes": 0,
      "got_out": 1,
      "duck": 1,
      "overs": 0.0,
      "runs_conceded": 0,
      "wickets": 0,
      "maidens": 0,
      "lbw_bowled": 0,
      "catches": 0,
      "stumpings": 0,
      "run_out_direct": 0,
      "run_out_assist": 0
    },
    "c11": {
      "played": true,
      "runs": 2,
      "balls": 9,
      "fours": 0,
      "sixes": 0,
      "got_out": 1,
      "duck": 0,
      "overs": 0.0,
      "runs_conceded": 0,
      "wickets": 0,
      "maidens": 0,
      "lbw_bowled": 0,
      "catches": 1,
      "stumpings": 0,
      "run_out_direct": 0,
      "run_out_assist": 0
    },
    "c02": {
      "played": true,
      "runs": 22,
      "balls": 17,
      "fours": 3,
      "sixes": 1,
      "got_out": 1,
      "duck": 0,
      "overs": 1.0,
      "runs_conceded": 7,
      "wickets": 0,
      "maidens": 0,
      "lbw_bowled": 0,
      "catches": 0,
      "stumpings": 0,
      "run_out_direct": 0,
      "run_out_assist": 0
    },
    "c08": {
      "played": true,
      "runs": 15,
      "balls": 9,
      "fours": 3,
      "sixes": 0,
      "got_out": 1,
      "duck": 0,
      "overs": 0.0,
      "runs_conceded": 0,
      "wickets": 0,
      "maidens": 0,
      "lbw_bowled": 0,
      "catches": 0,
      "stumpings": 0,
      "run_out_direct": 0,
      "run_out_assist": 0
    },
    "c13": {
      "played": true,
      "runs": 18,
      "balls": 6,
      "fours": 3,
      "sixes": 1,
      "got_out": 1,
      "duck": 0,
      "overs": 2.0,
      "runs_conceded": 28,
      "wickets": 0,
      "maidens": 0,
      "lbw_bowled": 0,
      "catches": 0,
      "stumpings": 0,
      "run_out_direct": 0,
      "run_out_assist": 0
    },
    "c20": {
      "played": true,
      "runs": 0,
      "balls": 0,
      "fours": 0,
      "sixes": 0,
      "got_out": 0,
      "duck": 0,
      "overs": 3.6666666666666665,
      "runs_conceded": 46,
      "wickets": 1,
      "maidens": 0,
      "lbw_bowled": 0,
      "catches": 0,
      "stumpings": 0,
      "run_out_direct": 0,
      "run_out_assist": 0
    },
    "c12": {
      "played": true,
      "runs": 0,
      "balls": 0,
      "fours": 0,
      "sixes": 0,
      "got_out": 0,
      "duck": 0,
      "overs": 4.0,
      "runs_conceded": 29,
      "wickets": 1,
      "maidens": 0,
      "lbw_bowled": 0,
      "catches": 0,
      "stumpings": 0,
      "run_out_direct": 0,
      "run_out_assist": 0
    },
    "c05": {
      "played": true,
      "runs": 0,
      "balls": 0,
      "fours": 0,
      "sixes": 0,
      "got_out": 0,
      "duck": 0,
      "overs": 3.0,
      "runs_conceded": 16,
      "wickets": 0,
      "maidens": 0,
      "lbw_bowled": 0,
      "catches": 0,
      "stumpings": 0,
      "run_out_direct": 0,
      "run_out_assist": 0
    },
    "ext_19807": {
      "played": true,
      "runs": 0,
      "balls": 0,
      "fours": 0,
      "sixes": 0,
      "got_out": 0,
      "duck": 0,
      "overs": 3.0,
      "runs_conceded": 36,
      "wickets": 0,
      "maidens": 0,
      "lbw_bowled": 0,
      "catches": 0,
      "stumpings": 0,
      "run_out_direct": 0,
      "run_out_assist": 0
    },
    "ext_10808": {
      "played": true,
      "runs": 0,
      "balls": 0,
      "fours": 0,
      "sixes": 0,
      "got_out": 0,
      "duck": 0,
      "overs": 4.0,
      "runs_conceded": 23,
      "wickets": 1,
      "maidens": 0,
      "lbw_bowled": 0,
      "catches": 0,
      "stumpings": 0,
      "run_out_direct": 0,
      "run_out_assist": 0
    },
    "g22": {
      "played": true,
      "runs": 0,
      "balls": 0,
      "fours": 0,
      "sixes": 0,
      "got_out": 0,
      "duck": 0,
      "overs": 4.0,
      "runs_conceded": 25,
      "wickets": 3,
      "maidens": 0,
      "lbw_bowled": 0,
      "catches": 0,
      "stumpings": 0,
      "run_out_direct": 0,
      "run_out_assist": 0
    },
    "ext_14596": {
      "played": true,
      "runs": 0,
      "balls": 0,
      "fours": 0,
      "sixes": 0,
      "got_out": 0,
      "duck": 0,
      "overs": 3.0,
      "runs_conceded": 22,
      "wickets": 1,
      "maidens": 0,
      "lbw_bowled": 0,
      "catches": 0,
      "stumpings": 0,
      "run_out_direct": 0,
      "run_out_assist": 0
    },
    "ext_8313": {
      "played": true,
      "runs": 0,
      "balls": 0,
      "fours": 0,
      "sixes": 0,
      "got_out": 0,
      "duck": 0,
      "overs": 4.0,
      "runs_conceded": 22,
      "wickets": 0,
      "maidens": 0,
      "lbw_bowled": 0,
      "catches": 2,
      "stumpings": 0,
      "run_out_direct": 0,
      "run_out_assist": 0
    },
    "ext_06f6eb": {
      "played": true,
      "runs": 0,
      "balls": 0,
      "fours": 0,
      "sixes": 0,
      "got_out": 0,
      "duck": 0,
      "overs": 4.0,
      "runs_conceded": 43,
      "wickets": 2,
      "maidens": 0,
      "lbw_bowled": 1,
      "catches": 0,
      "stumpings": 0,
      "run_out_direct": 0,
      "run_out_assist": 0
    },
    "g03": {
      "played": true,
      "runs": 0,
      "balls": 0,
      "fours": 0,
      "sixes": 0,
      "got_out": 0,
      "duck": 0,
      "overs": 1.0,
      "runs_conceded": 21,
      "wickets": 0,
      "maidens": 0,
      "lbw_bowled": 0,
      "catches": 0,
      "stumpings": 0,
      "run_out_direct": 0,
      "run_out_assist": 0
    },
    "g02": {
      "played": true,
      "runs": 87,
      "balls": 46,
      "fours": 4,
      "sixes": 7,
      "got_out": 1,
      "duck": 0,
      "overs": 0.0,
      "runs_conceded": 0,
      "wickets": 0,
      "maidens": 0,
      "lbw_bowled": 0,
      "catches": 0,
      "stumpings": 0,
      "run_out_direct": 0,
      "run_out_assist": 0
    },
    "g01": {
      "played": true,
      "runs": 33,
      "balls": 23,
      "fours": 1,
      "sixes": 3,
      "got_out": 1,
      "duck": 0,
      "overs": 0.0,
      "runs_conceded": 0,
      "wickets": 0,
      "maidens": 0,
      "lbw_bowled": 0,
      "catches": 1,
      "stumpings": 0,
      "run_out_direct": 0,
      "run_out_assist": 0
    },
    "g11": {
      "played": true,
      "runs": 39,
      "balls": 30,
      "fours": 4,
      "sixes": 1,
      "got_out": 0,
      "duck": 0,
      "overs": 0.0,
      "runs_conceded": 0,
      "wickets": 0,
      "maidens": 0,
      "lbw_bowled": 0,
      "catches": 2,
      "stumpings": 0,
      "run_out_direct": 0,
      "run_out_assist": 0
    },
    "ext_10945": {
      "played": true,
      "runs": 1,
      "balls": 1,
      "fours": 0,
      "sixes": 0,
      "got_out": 0,
      "duck": 0,
      "overs": 0.0,
      "runs_conceded": 0,
      "wickets": 0,
      "maidens": 0,
      "lbw_bowled": 0,
      "catches": 0,
      "stumpings": 0,
      "run_out_direct": 0,
      "run_out_assist": 0
    },
    "g21": {
      "played": true,
      "runs": 0,
      "balls": 0,
      "fours": 0,
      "sixes": 0,
      "got_out": 0,
      "duck": 0,
      "overs": 0.0,
      "runs_conceded": 0,
      "wickets": 0,
      "maidens": 0,
      "lbw_bowled": 0,
      "catches": 1,
      "stumpings": 0,
      "run_out_direct": 0,
      "run_out_assist": 0
    }
  }
}